cleanit/__init__.py
cleanit/cli.py
cleanit/config.py
cleanit/data/__init__.py
cleanit/data/cleanit-no-lyrics.yml
cleanit/data/cleanit-no-sdh.yml
cleanit/data/cleanit-no-spam.de.yml
cleanit/data/cleanit-no-spam.en.yml
cleanit/data/cleanit-no-spam.pt.yml
cleanit/data/cleanit-no-spam.yml
cleanit/data/cleanit-no-style.yml
cleanit/data/cleanit-ocr.en.yml
cleanit/data/cleanit-ocr.pt.yml
cleanit/data/cleanit-ocr.yml
cleanit/data/cleanit-tidy.en.yml
cleanit/data/cleanit-tidy.pt.yml
cleanit/data/cleanit-tidy.yml
cleanit/data/cleanit.yml
cleanit/rule.py
cleanit/schema.py
cleanit/subtitle.py
cleanit/utils.py
cleanit-0.4.5.dist-info/entry_points.txt
cleanit-0.4.5.dist-info/METADATA
cleanit-0.4.5.dist-info/LICENSE
cleanit-0.4.5.dist-info/WHEEL
cleanit-0.4.5.dist-info/RECORD
