Metadata-Version: 2.1
Name: cleanit
Version: 0.4.5
Summary: Subtitles extremely clean
Home-page: https://github.com/ratoaq2/cleanit
License: Apache-2.0
Keywords: subtitle,subtitles,clean,denylist,replace,ocr,fix,tidy
Author: Rato
Requires-Python: >=3.8.1,<4.0.0
Classifier: Development Status :: 5 - Production/Stable
Classifier: Intended Audience :: Developers
Classifier: License :: OSI Approved :: Apache Software License
Classifier: Operating System :: OS Independent
Classifier: Programming Language :: Python
Classifier: Programming Language :: Python :: 3
Classifier: Programming Language :: Python :: 3.9
Classifier: Programming Language :: Python :: 3.10
Classifier: Programming Language :: Python :: 3.11
Classifier: Programming Language :: Python :: 3
Classifier: Programming Language :: Python :: 3 :: Only
Classifier: Programming Language :: Python :: 3.10
Classifier: Programming Language :: Python :: 3.11
Classifier: Programming Language :: Python :: 3.8
Classifier: Programming Language :: Python :: 3.9
Classifier: Topic :: Multimedia :: Video
Classifier: Topic :: Software Development :: Libraries :: Python Modules
Requires-Dist: appdirs (>=1.4.4,<2.0.0)
Requires-Dist: babelfish (>=0.6.0,<0.7.0)
Requires-Dist: chardet (>=5.1.0,<6.0.0)
Requires-Dist: click (>=8.1.3,<9.0.0)
Requires-Dist: jsonschema (>=4.17.3,<5.0.0)
Requires-Dist: pysrt (>=1.1.2,<2.0.0)
Requires-Dist: pyyaml (>=6.0,<7.0)
Project-URL: Repository, https://github.com/ratoaq2/cleanit
